[
  {
    "To": "f01016254",
    "Height": 3054823,
    "Gas": {
      "tg": 66450641,
      "tt": 1300934
    }
  },
  {
    "To": "f01016882",
    "Height": 3054823,
    "Gas": {
      "tg": 29032638,
      "tt": 635733
    }
  },
  {
    "To": "f01027268",
    "Height": 3054823,
    "Gas": {
      "tg": 52868882,
      "tt": 1154511
    }
  },
  {
    "To": "f01089828",
    "Height": 3054823,
    "Gas": {
      "tg": 65161086,
      "tt": 1256545
    }
  },
  {
    "To": "f01110111",
    "Height": 3054823,
    "Gas": {
      "tg": 48961848,
      "tt": 1064201
    }
  },
  {
    "To": "f0113331",
    "Height": 3054823,
    "Gas": {
      "tg": 50129265,
      "tt": 1103784
    }
  },
  {
    "To": "f01137855",
    "Height": 3054823,
    "Gas": {
      "tg": 33387659,
      "tt": 729103
    }
  },
  {
    "To": "f01139383",
    "Height": 3054823,
    "Gas": {
      "tg": 39095868,
      "tt": 861213
    }
  },
  {
    "To": "f01161077",
    "Height": 3054823,
    "Gas": {
      "tg": 32947314,
      "tt": 719391
    }
  },
  {
    "To": "f01162221",
    "Height": 3054823,
    "Gas": {
      "tg": 52876039,
      "tt": 1156404
    }
  },
  {
    "To": "f01169722",
    "Height": 3054823,
    "Gas": {
      "tg": 45554577,
      "tt": 980899
    }
  },
  {
    "To": "f01208503",
    "Height": 3054823,
    "Gas": {
      "tg": 65765452,
      "tt": 1284250
    }
  },
  {
    "To": "f01208636",
    "Height": 3054823,
    "Gas": {
      "tg": 53473338,
      "tt": 1162690
    }
  },
  {
    "To": "f0124696",
    "Height": 3054823,
    "Gas": {
      "tg": 38702450,
      "tt": 833350
    }
  },
  {
    "To": "f01378236",
    "Height": 3054823,
    "Gas": {
      "tg": 53725363,
      "tt": 1177035
    }
  },
  {
    "To": "f0145503",
    "Height": 3054823,
    "Gas": {
      "tg": 49829658,
      "tt": 1074368
    }
  },
  {
    "To": "f0145784",
    "Height": 3054823,
    "Gas": {
      "tg": 48018707,
      "tt": 1040743
    }
  },
  {
    "To": "f0146301",
    "Height": 3054823,
    "Gas": {
      "tg": 64399204,
      "tt": 1255842
    }
  },
  {
    "To": "f0146751",
    "Height": 3054823,
    "Gas": {
      "tg": 51333004,
      "tt": 1102742
    }
  },
  {
    "To": "f01578658",
    "Height": 3054823,
    "Gas": {
      "tg": 53795381,
      "tt": 1174128
    }
  },
  {
    "To": "f0159632",
    "Height": 3054823,
    "Gas": {
      "tg": 48766877,
      "tt": 1054687
    }
  },
  {
    "To": "f0162183",
    "Height": 3054823,
    "Gas": {
      "tg": 52382728,
      "tt": 1127709
    }
  },
  {
    "To": "f01654059",
    "Height": 3054823,
    "Gas": {
      "tg": 53542482,
      "tt": 1163558
    }
  },
  {
    "To": "f01711909",
    "Height": 3054823,
    "Gas": {
      "tg": 65635099,
      "tt": 1280990
    }
  },
  {
    "To": "f01713152",
    "Height": 3054823,
    "Gas": {
      "tg": 67667739,
      "tt": 1351364
    }
  },
  {
    "To": "f0172300",
    "Height": 3054823,
    "Gas": {
      "tg": 57157471,
      "tt": 1322345
    }
  },
  {
    "To": "f01731371",
    "Height": 3054823,
    "Gas": {
      "tg": 67037181,
      "tt": 1276617
    }
  },
  {
    "To": "f01737472",
    "Height": 3054823,
    "Gas": {
      "tg": 65949800,
      "tt": 1294942
    }
  },
  {
    "To": "f01741815",
    "Height": 3054823,
    "Gas": {
      "tg": 53968914,
      "tt": 1175060
    }
  },
  {
    "To": "f01742921",
    "Height": 3054823,
    "Gas": {
      "tg": 66051619,
      "tt": 1285763
    }
  },
  {
    "To": "f01766263",
    "Height": 3054823,
    "Gas": {
      "tg": 67810216,
      "tt": 1365780
    }
  },
  {
    "To": "f01830824",
    "Height": 3054823,
    "Gas": {
      "tg": 54242071,
      "tt": 1173817
    }
  },
  {
    "To": "f01831595",
    "Height": 3054823,
    "Gas": {
      "tg": 69013386,
      "tt": 1418285
    }
  },
  {
    "To": "f01836766",
    "Height": 3054823,
    "Gas": {
      "tg": 73057796,
      "tt": 1611198
    }
  },
  {
    "To": "f01862232",
    "Height": 3054823,
    "Gas": {
      "tg": 53827644,
      "tt": 1178247
    }
  },
  {
    "To": "f01880897",
    "Height": 3054823,
    "Gas": {
      "tg": 55266250,
      "tt": 1189688
    }
  },
  {
    "To": "f01926792",
    "Height": 3054823,
    "Gas": {
      "tg": 55543977,
      "tt": 1220141
    }
  },
  {
    "To": "f01972376",
    "Height": 3054823,
    "Gas": {
      "tg": 55306920,
      "tt": 1186529
    }
  },
  {
    "To": "f01972988",
    "Height": 3054823,
    "Gas": {
      "tg": 76913469,
      "tt": 1430928
    }
  },
  {
    "To": "f02020908",
    "Height": 3054823,
    "Gas": {
      "tg": 54607641,
      "tt": 1240855
    }
  },
  {
    "To": "f02037537",
    "Height": 3054823,
    "Gas": {
      "tg": 56311749,
      "tt": 1221576
    }
  },
  {
    "To": "f02038072",
    "Height": 3054823,
    "Gas": {
      "tg": 54566018,
      "tt": 1187111
    }
  },
  {
    "To": "f02040772",
    "Height": 3054823,
    "Gas": {
      "tg": 53015070,
      "tt": 1223599
    }
  },
  {
    "To": "f02062851",
    "Height": 3054823,
    "Gas": {
      "tg": 66860221,
      "tt": 1393075
    }
  },
  {
    "To": "f02126560",
    "Height": 3054823,
    "Gas": {
      "tg": 66551067,
      "tt": 1272174
    }
  },
  {
    "To": "f02130191",
    "Height": 3054823,
    "Gas": {
      "tg": 153749317,
      "tt": 9450683
    }
  },
  {
    "To": "f0214334",
    "Height": 3054823,
    "Gas": {
      "tg": 52346046,
      "tt": 1126358
    }
  },
  {
    "To": "f0218072",
    "Height": 3054823,
    "Gas": {
      "tg": 52076673,
      "tt": 1127789
    }
  },
  {
    "To": "f02227731",
    "Height": 3054823,
    "Gas": {
      "tg": 26253125,
      "tt": 582977
    }
  },
  {
    "To": "f023843",
    "Height": 3054823,
    "Gas": {
      "tg": 51549663,
      "tt": 1163038
    }
  },
  {
    "To": "f0241536",
    "Height": 3054823,
    "Gas": {
      "tg": 28115521,
      "tt": 612587
    }
  },
  {
    "To": "f0392992",
    "Height": 3054823,
    "Gas": {
      "tg": 52630605,
      "tt": 1150686
    }
  },
  {
    "To": "f0409069",
    "Height": 3054823,
    "Gas": {
      "tg": 66517700,
      "tt": 1300562
    }
  },
  {
    "To": "f0428184",
    "Height": 3054823,
    "Gas": {
      "tg": 37063820,
      "tt": 810606
    }
  },
  {
    "To": "f042855",
    "Height": 3054823,
    "Gas": {
      "tg": 47932440,
      "tt": 1029230
    }
  },
  {
    "To": "f0480936",
    "Height": 3054823,
    "Gas": {
      "tg": 52841047,
      "tt": 1134593
    }
  },
  {
    "To": "f053140",
    "Height": 3054823,
    "Gas": {
      "tg": 51794836,
      "tt": 1117628
    }
  },
  {
    "To": "f066104",
    "Height": 3054823,
    "Gas": {
      "tg": 64475038,
      "tt": 1266203
    }
  },
  {
    "To": "f0694396",
    "Height": 3054823,
    "Gas": {
      "tg": 48859335,
      "tt": 1056939
    }
  },
  {
    "To": "f0697913",
    "Height": 3054823,
    "Gas": {
      "tg": 52824969,
      "tt": 1147018
    }
  },
  {
    "To": "f0730942",
    "Height": 3054823,
    "Gas": {
      "tg": 66021681,
      "tt": 1305972
    }
  },
  {
    "To": "f0814012",
    "Height": 3054823,
    "Gas": {
      "tg": 24920894,
      "tt": 575989
    }
  },
  {
    "To": "f0839084",
    "Height": 3054823,
    "Gas": {
      "tg": 67408717,
      "tt": 1332268
    }
  },
  {
    "To": "f0844916",
    "Height": 3054823,
    "Gas": {
      "tg": 52832487,
      "tt": 1148818
    }
  },
  {
    "To": "f0874057",
    "Height": 3054823,
    "Gas": {
      "tg": 53642886,
      "tt": 1167874
    }
  },
  {
    "To": "f0879756",
    "Height": 3054823,
    "Gas": {
      "tg": 65083815,
      "tt": 1257826
    }
  },
  {
    "To": "f089167",
    "Height": 3054823,
    "Gas": {
      "tg": 51941826,
      "tt": 1117430
    }
  },
  {
    "To": "f091959",
    "Height": 3054823,
    "Gas": {
      "tg": 51434322,
      "tt": 1100967
    }
  },
  {
    "To": "f098664",
    "Height": 3054823,
    "Gas": {
      "tg": 51666251,
      "tt": 1107532
    }
  },
  {
    "To": "f099132",
    "Height": 3054823,
    "Gas": {
      "tg": 64305070,
      "tt": 1276766
    }
  }
]
