[
  {
    "To": "f0101016",
    "Height": 3055359,
    "Gas": {
      "tg": 50624725,
      "tt": 1075782
    }
  },
  {
    "To": "f01021756",
    "Height": 3055359,
    "Gas": {
      "tg": 51779616,
      "tt": 1123961
    }
  },
  {
    "To": "f01025778",
    "Height": 3055359,
    "Gas": {
      "tg": 50881644,
      "tt": 1097300
    }
  },
  {
    "To": "f01062274",
    "Height": 3055359,
    "Gas": {
      "tg": 51392544,
      "tt": 1109714
    }
  },
  {
    "To": "f01071719",
    "Height": 3055359,
    "Gas": {
      "tg": 52080687,
      "tt": 1126227
    }
  },
  {
    "To": "f01077708",
    "Height": 3055359,
    "Gas": {
      "tg": 59207924,
      "tt": 1153934
    }
  },
  {
    "To": "f0109272",
    "Height": 3055359,
    "Gas": {
      "tg": 27609960,
      "tt": 593672
    }
  },
  {
    "To": "f0111343",
    "Height": 3055359,
    "Gas": {
      "tg": 49783413,
      "tt": 1070919
    }
  },
  {
    "To": "f0116095",
    "Height": 3055359,
    "Gas": {
      "tg": 32330622,
      "tt": 695506
    }
  },
  {
    "To": "f01179972",
    "Height": 3055359,
    "Gas": {
      "tg": 63969668,
      "tt": 1229744
    }
  },
  {
    "To": "f01206253",
    "Height": 3055359,
    "Gas": {
      "tg": 52586011,
      "tt": 1149738
    }
  },
  {
    "To": "f01218989",
    "Height": 3055359,
    "Gas": {
      "tg": 64453281,
      "tt": 1247845
    }
  },
  {
    "To": "f01227998",
    "Height": 3055359,
    "Gas": {
      "tg": 66748830,
      "tt": 1369845
    }
  },
  {
    "To": "f0123536",
    "Height": 3055359,
    "Gas": {
      "tg": 63345284,
      "tt": 1205303
    }
  },
  {
    "To": "f01319803",
    "Height": 3055359,
    "Gas": {
      "tg": 66379510,
      "tt": 1334943
    }
  },
  {
    "To": "f01384139",
    "Height": 3055359,
    "Gas": {
      "tg": 69720863,
      "tt": 1480871
    }
  },
  {
    "To": "f01438277",
    "Height": 3055359,
    "Gas": {
      "tg": 42133976,
      "tt": 917687
    }
  },
  {
    "To": "f01452388",
    "Height": 3055359,
    "Gas": {
      "tg": 64914765,
      "tt": 1256815
    }
  },
  {
    "To": "f0151436",
    "Height": 3055359,
    "Gas": {
      "tg": 63211305,
      "tt": 1197824
    }
  },
  {
    "To": "f0159711",
    "Height": 3055359,
    "Gas": {
      "tg": 51144656,
      "tt": 1093754
    }
  },
  {
    "To": "f01706163",
    "Height": 3055359,
    "Gas": {
      "tg": 64805784,
      "tt": 1326251
    }
  },
  {
    "To": "f01707814",
    "Height": 3055359,
    "Gas": {
      "tg": 65689605,
      "tt": 1305069
    }
  },
  {
    "To": "f01759262",
    "Height": 3055359,
    "Gas": {
      "tg": 66284627,
      "tt": 1285451
    }
  },
  {
    "To": "f01825475",
    "Height": 3055359,
    "Gas": {
      "tg": 53176743,
      "tt": 1149510
    }
  },
  {
    "To": "f01831658",
    "Height": 3055359,
    "Gas": {
      "tg": 52873969,
      "tt": 1155878
    }
  },
  {
    "To": "f01904030",
    "Height": 3055359,
    "Gas": {
      "tg": 62467356,
      "tt": 1206461
    }
  },
  {
    "To": "f01937538",
    "Height": 3055359,
    "Gas": {
      "tg": 66144621,
      "tt": 1311480
    }
  },
  {
    "To": "f01941229",
    "Height": 3055359,
    "Gas": {
      "tg": 65409974,
      "tt": 1263571
    }
  },
  {
    "To": "f01943663",
    "Height": 3055359,
    "Gas": {
      "tg": 66299375,
      "tt": 1277227
    }
  },
  {
    "To": "f01943941",
    "Height": 3055359,
    "Gas": {
      "tg": 53361413,
      "tt": 1162888
    }
  },
  {
    "To": "f01986387",
    "Height": 3055359,
    "Gas": {
      "tg": 65899079,
      "tt": 1315471
    }
  },
  {
    "To": "f01992431",
    "Height": 3055359,
    "Gas": {
      "tg": 53257171,
      "tt": 1165504
    }
  },
  {
    "To": "f01999672",
    "Height": 3055359,
    "Gas": {
      "tg": 53448666,
      "tt": 1160953
    }
  },
  {
    "To": "f02038720",
    "Height": 3055359,
    "Gas": {
      "tg": 58465765,
      "tt": 1430575
    }
  },
  {
    "To": "f02055660",
    "Height": 3055359,
    "Gas": {
      "tg": 54698491,
      "tt": 1250021
    }
  },
  {
    "To": "f02078382",
    "Height": 3055359,
    "Gas": {
      "tg": 65130449,
      "tt": 1295200
    }
  },
  {
    "To": "f02085743",
    "Height": 3055359,
    "Gas": {
      "tg": 55402959,
      "tt": 1212327
    }
  },
  {
    "To": "f02088858",
    "Height": 3055359,
    "Gas": {
      "tg": 64571813,
      "tt": 1253149
    }
  },
  {
    "To": "f02105219",
    "Height": 3055359,
    "Gas": {
      "tg": 76842208,
      "tt": 2641278
    }
  },
  {
    "To": "f02128661",
    "Height": 3055359,
    "Gas": {
      "tg": 52886937,
      "tt": 1305469
    }
  },
  {
    "To": "f0216922",
    "Height": 3055359,
    "Gas": {
      "tg": 51559836,
      "tt": 1102519
    }
  },
  {
    "To": "f02182085",
    "Height": 3055359,
    "Gas": {
      "tg": 73814651,
      "tt": 1521914
    }
  },
  {
    "To": "f02224517",
    "Height": 3055359,
    "Gas": {
      "tg": 89968547,
      "tt": 3607128
    }
  },
  {
    "To": "f02230983",
    "Height": 3055359,
    "Gas": {
      "tg": 54299696,
      "tt": 1254963
    }
  },
  {
    "To": "f02236570",
    "Height": 3055359,
    "Gas": {
      "tg": 54446360,
      "tt": 1256639
    }
  },
  {
    "To": "f02252173",
    "Height": 3055359,
    "Gas": {
      "tg": 25398701,
      "tt": 571227
    }
  },
  {
    "To": "f0333333",
    "Height": 3055359,
    "Gas": {
      "tg": 53950172,
      "tt": 1184817
    }
  },
  {
    "To": "f0406322",
    "Height": 3055359,
    "Gas": {
      "tg": 51039983,
      "tt": 1094547
    }
  },
  {
    "To": "f0410701",
    "Height": 3055359,
    "Gas": {
      "tg": 75930561,
      "tt": 1590693
    }
  },
  {
    "To": "f0417826",
    "Height": 3055359,
    "Gas": {
      "tg": 30462498,
      "tt": 667392
    }
  },
  {
    "To": "f0432345",
    "Height": 3055359,
    "Gas": {
      "tg": 65220121,
      "tt": 1252177
    }
  },
  {
    "To": "f0451341",
    "Height": 3055359,
    "Gas": {
      "tg": 63631127,
      "tt": 1222782
    }
  },
  {
    "To": "f0472863",
    "Height": 3055359,
    "Gas": {
      "tg": 51900821,
      "tt": 1113686
    }
  },
  {
    "To": "f0510701",
    "Height": 3055359,
    "Gas": {
      "tg": 51864765,
      "tt": 1113992
    }
  },
  {
    "To": "f062931",
    "Height": 3055359,
    "Gas": {
      "tg": 63364007,
      "tt": 1315930
    }
  },
  {
    "To": "f0694928",
    "Height": 3055359,
    "Gas": {
      "tg": 65099906,
      "tt": 1244894
    }
  },
  {
    "To": "f0699021",
    "Height": 3055359,
    "Gas": {
      "tg": 64301239,
      "tt": 1241856
    }
  },
  {
    "To": "f0729297",
    "Height": 3055359,
    "Gas": {
      "tg": 49919320,
      "tt": 1082442
    }
  },
  {
    "To": "f0753055",
    "Height": 3055359,
    "Gas": {
      "tg": 30596392,
      "tt": 670149
    }
  },
  {
    "To": "f0753366",
    "Height": 3055359,
    "Gas": {
      "tg": 30431954,
      "tt": 658913
    }
  },
  {
    "To": "f0757610",
    "Height": 3055359,
    "Gas": {
      "tg": 46482941,
      "tt": 998233
    }
  },
  {
    "To": "f082356",
    "Height": 3055359,
    "Gas": {
      "tg": 50264891,
      "tt": 1080940
    }
  },
  {
    "To": "f085437",
    "Height": 3055359,
    "Gas": {
      "tg": 47244218,
      "tt": 1045440
    }
  },
  {
    "To": "f0884781",
    "Height": 3055359,
    "Gas": {
      "tg": 52199964,
      "tt": 1126548
    }
  },
  {
    "To": "f095997",
    "Height": 3055359,
    "Gas": {
      "tg": 51876828,
      "tt": 1115947
    }
  },
  {
    "To": "f099369",
    "Height": 3055359,
    "Gas": {
      "tg": 62371159,
      "tt": 1184659
    }
  }
]
